django_selectel_storage/__init__.py
django_selectel_storage/apps.py
django_selectel_storage/compat.py
django_selectel_storage/exceptions.py
django_selectel_storage/selectel.py
django_selectel_storage/storage.py
django_selectel_storage/utils.py
django_selectel_storage-1.0.2.dist-info/LICENSE
django_selectel_storage-1.0.2.dist-info/WHEEL
django_selectel_storage-1.0.2.dist-info/METADATA
django_selectel_storage-1.0.2.dist-info/RECORD
