Metadata-Version: 2.1
Name: django-selectel-storage
Version: 1.0.2
Summary: A Django storage backend allowing you to easily save user-generated and static files inside Selectel Cloud storage rather than a local filesystem, as Django does by default.
Home-page: https://github.com/marazmiki/django-selectel-storage
License: MIT
Keywords: django,selectel,storage,remote storage,http
Author: Mikhail Porokhovnichenko
Author-email: marazmiki@gmail.com
Requires-Python: >=2.7, !=3.0.*, !=3.1.*, !=3.2.*, !=3.3.*, !=3.4.*
Classifier: Development Status :: 5 - Production/Stable
Classifier: Environment :: Web Environment
Classifier: Framework :: Django
Classifier: Framework :: Django :: 1.11
Classifier: Framework :: Django :: 2.0
Classifier: Framework :: Django :: 2.1
Classifier: Framework :: Django :: 2.2
Classifier: Framework :: Django :: 3.0
Classifier: License :: OSI Approved :: BSD License
Classifier: License :: OSI Approved :: MIT License
Classifier: Programming Language :: Python :: 2
Classifier: Programming Language :: Python :: 2.7
Classifier: Programming Language :: Python :: 3
Classifier: Programming Language :: Python :: 3.5
Classifier: Programming Language :: Python :: 3.6
Classifier: Programming Language :: Python :: 3.7
Classifier: Programming Language :: Python :: 3.8
Classifier: Topic :: Internet :: WWW/HTTP
Classifier: Topic :: Internet :: WWW/HTTP :: Dynamic Content
Requires-Dist: requests (>=2.23.0,<3.0.0)
Project-URL: Repository, https://github.com/marazmiki/django-selectel-storage
